[{"valx":1246,"globalY":670,"isWalkable":true,"globalX":1248,"floorMap":"Campus Map","name":"Fountain","isPlace":true,"type":"Place","valz":0,"building":"Campus","valy":670},{"valx":1231,"globalY":567,"isWalkable":true,"globalX":1231,"floorMap":"Campus Map","name":"Olin Hall","isPlace":true,"type":"Place","valz":0,"building":"Campus","valy":567},{"valx":1263,"globalY":573,"isWalkable":true,"globalX":1262,"floorMap":"Campus Map","name":"Campus:1263:574:0","isPlace":false,"type":"Place","valz":0,"building":"Campus","valy":574},{"valx":1253,"globalY":637,"isWalkable":true,"globalX":1252,"floorMap":"Campus Map","name":"Campus:1253:637:0","isPlace":false,"type":"Place","valz":0,"building":"Campus","valy":637},{"valx":1310,"globalY":610,"isWalkable":true,"globalX":1310,"floorMap":"Campus Map","name":"Salisbury Labs","isPlace":true,"type":"Place","valz":0,"building":"Campus","valy":610},{"valx":1176,"globalY":619,"isWalkable":true,"globalX":1176,"floorMap":"Campus Map","name":"Campus:1176:619:0","isPlace":false,"type":"Place","valz":0,"building":"Campus","valy":619},{"valx":1140,"globalY":614,"isWalkable":true,"globalX":1140,"floorMap":"Campus Map","name":"Campus Center Front Entrance Right","isPlace":false,"type":"Transition Point","valz":0,"building":"Campus","valy":614},{"valx":1122,"globalY":637,"isWalkable":true,"globalX":1122,"floorMap":"Campus Map","name":"Campus Center Front Entrance Left","isPlace":false,"type":"Transition Point","valz":0,"building":"Campus","valy":637},{"valx":1280,"globalY":674,"isWalkable":true,"globalX":1280,"floorMap":"Campus Map","name":"Campus:1280:674:0","isPlace":false,"type":"Place","valz":0,"building":"Campus","valy":674},{"valx":1277,"globalY":690,"isWalkable":true,"globalX":1277,"floorMap":"Campus Map","name":"Project Center Entrance","isPlace":false,"type":"Transition Point","valz":0,"building":"Campus","valy":690},{"valx":1119,"globalY":650,"isWalkable":true,"globalX":1119,"floorMap":"Campus Map","name":"Campus:1119:650:0","isPlace":false,"type":"Place","valz":0,"building":"Campus","valy":650},{"valx":1084,"globalY":572,"isWalkable":true,"globalX":1084,"floorMap":"Campus Map","name":"Campus Center 1st Floor Entrance","isPlace":false,"type":"Transition Point","valz":-1,"building":"Campus","valy":572},{"valx":802,"globalY":715,"isWalkable":true,"globalX":802,"floorMap":"Campus Map","name":"Recreational Center","isPlace":true,"type":"Place","valz":0,"building":"Campus","valy":715},{"valx":880,"globalY":826,"isWalkable":true,"globalX":880,"floorMap":"Campus Map","name":"Seal","isPlace":true,"type":"Place","valz":0,"building":"Campus","valy":826},{"valx":1050,"globalY":854,"isWalkable":true,"globalX":1056,"floorMap":"Campus Map","name":"Bartlett Center","isPlace":true,"type":"Place","valz":0,"building":"Campus","valy":854},{"valx":879,"globalY":722,"isWalkable":true,"globalX":879,"floorMap":"Campus Map","name":"Harrington Auditorium","isPlace":true,"type":"Place","valz":0,"building":"Campus","valy":722},{"valx":1191,"globalY":744,"isWalkable":true,"globalX":1191,"floorMap":"Campus Map","name":"Higgins Labs","isPlace":true,"type":"Place","valz":0,"building":"Campus","valy":744},{"valx":1137,"globalY":921,"isWalkable":true,"globalX":1137,"floorMap":"Campus Map","name":"Alden Hall","isPlace":true,"type":"Place","valz":0,"building":"Campus","valy":921},{"valx":1020,"globalY":973,"isWalkable":true,"globalX":1020,"floorMap":"Campus Map","name":"Riley Hall","isPlace":true,"type":"Place","valz":0,"building":"Campus","valy":973},{"valx":752,"globalY":904,"isWalkable":true,"globalX":752,"floorMap":"Campus Map","name":"Morgan/Daniels Hall","isPlace":true,"type":"Place","valz":0,"building":"Campus","valy":904},{"valx":1441,"globalY":576,"isWalkable":true,"globalX":1441,"floorMap":"Campus Map","name":"Fuller Labs","isPlace":true,"type":"Place","valz":-1,"building":"Campus","valy":576},{"valx":1384,"globalY":738,"isWalkable":true,"globalX":1384,"floorMap":"Campus Map","name":"Washburn Shops","isPlace":true,"type":"Place","valz":0,"building":"Campus","valy":738},{"valx":1224,"globalY":431,"isWalkable":true,"globalX":1224,"floorMap":"Campus Map","name":"Goddard Hall","isPlace":true,"type":"Place","valz":0,"building":"Campus","valy":431},{"valx":834,"globalY":945,"isWalkable":true,"globalX":834,"floorMap":"Campus Map","name":"Daniels Hall","isPlace":true,"type":"Place","valz":0,"building":"Campus","valy":945},{"valx":1613,"globalY":622,"isWalkable":true,"globalX":1613,"floorMap":"Campus Map","name":"Kaven Hall","isPlace":true,"type":"Place","valz":-4,"building":"Campus","valy":622},{"valx":1051,"globalY":723,"isWalkable":true,"globalX":1051,"floorMap":"Campus Map","name":"Alumni Gym","isPlace":true,"type":"Place","valz":0,"building":"Campus","valy":723},{"valx":1261,"globalY":584,"isWalkable":true,"globalX":1261,"floorMap":"Campus Map","name":"Campus:1261:584:0","isPlace":false,"type":"Place","valz":0,"building":"Campus","valy":584},{"valx":1159,"globalY":615,"isWalkable":true,"globalX":1159,"floorMap":"Campus Map","name":"Campus:1159:615:0","isPlace":false,"type":"Place","valz":0,"building":"Campus","valy":615},{"valx":1185,"globalY":474,"isWalkable":true,"globalX":1185,"floorMap":"Campus Map","name":"Campus:1185:474:0","isPlace":false,"type":"Place","valz":0,"building":"Campus","valy":474},{"valx":1179,"globalY":658,"isWalkable":true,"globalX":1179,"floorMap":"Campus Map","name":"Campus:1179:658:0","isPlace":false,"type":"Place","valz":0,"building":"Campus","valy":658},{"valx":1147,"globalY":652,"isWalkable":true,"globalX":1147,"floorMap":"Campus Map","name":"Campus:1147:652:0","isPlace":false,"type":"Place","valz":0,"building":"Campus","valy":652},{"valx":1312,"globalY":572,"isWalkable":true,"globalX":1312,"floorMap":"Campus Map","name":"Campus:1312:572:0","isPlace":false,"type":"Place","valz":0,"building":"Campus","valy":572},{"valx":1328,"globalY":561,"isWalkable":true,"globalX":1328,"floorMap":"Campus Map","name":"Campus:1328:572:-1","isPlace":false,"type":"Place","valz":-1,"building":"Campus","valy":561},{"valx":1233,"globalY":750,"isWalkable":true,"globalX":1233,"floorMap":"Campus Map","name":"Campus:1233:750:0","isPlace":false,"type":"Place","valz":-1,"building":"Campus","valy":750},{"valx":1338,"globalY":940,"isWalkable":true,"globalX":1338,"floorMap":"Campus Map","name":"Boynton Hall Main Entrance","isPlace":false,"type":"Transition Point","valz":1,"building":"Campus","valy":940},{"valx":1205,"globalY":928,"isWalkable":true,"globalX":1205,"floorMap":"Campus Map","name":"Bridge","isPlace":true,"type":"Place","valz":0,"building":"Campus","valy":928},{"valx":1334,"globalY":508,"isWalkable":true,"globalX":1334,"floorMap":"Campus Map","name":"Atwater Kent Front Entrance","isPlace":false,"type":"Transition Point","valz":-1,"building":"Campus","valy":508},{"valx":1273,"globalY":509,"isWalkable":true,"globalX":1273,"floorMap":"Campus Map","name":"Campus:1273:509:-1","isPlace":false,"type":"Place","valz":-1,"building":"Campus","valy":509},{"valx":1282,"globalY":494,"isWalkable":true,"globalX":1282,"floorMap":"Campus Map","name":"Campus:1282:494:-1","isPlace":false,"type":"Place","valz":-1,"building":"Campus","valy":494},{"valx":1308,"globalY":500,"isWalkable":true,"globalX":1308,"floorMap":"Campus Map","name":"Campus:1308:500:-1","isPlace":false,"type":"Place","valz":-1,"building":"Campus","valy":500},{"valx":1332,"globalY":515,"isWalkable":true,"globalX":1330,"floorMap":"Campus Map","name":"Campus:1330:515:-1","isPlace":false,"type":"Place","valz":-1,"building":"Campus","valy":512},{"valx":1270,"globalY":535,"isWalkable":true,"globalX":1270,"floorMap":"Campus Map","name":"Campus:1270:535:0","isPlace":false,"type":"Place","valz":-1,"building":"Campus","valy":535},{"valx":1224,"globalY":806,"isWalkable":true,"globalX":1224,"floorMap":"Campus Map","name":"Campus:1224:806:0","isPlace":false,"type":"Place","valz":0,"building":"Campus","valy":806},{"valx":1104,"globalY":739,"isWalkable":true,"globalX":1104,"floorMap":"Campus Map","name":"Campus:1104:739:0","isPlace":false,"type":"Place","valz":0,"building":"Campus","valy":739},{"valx":1193,"globalY":434,"isWalkable":true,"globalX":1193,"floorMap":"Campus Map","name":"Campus:11193:434:0","isPlace":false,"type":"Place","valz":0,"building":"Campus","valy":434},{"valx":1223,"globalY":440,"isWalkable":true,"globalX":1222,"floorMap":"Campus Map","name":"Campus:1222:440:0","isPlace":false,"type":"Place","valz":0,"building":"Campus","valy":438},{"valx":1396,"globalY":533,"isWalkable":true,"globalX":1396,"floorMap":"Campus Map","name":"Atwater Kent Side Entrance","isPlace":false,"type":"Transition Point","valz":-1,"building":"Campus","valy":533},{"valx":1343,"globalY":684,"isWalkable":true,"globalX":1343,"floorMap":"Campus Map","name":"Campus:1343:684:0","isPlace":false,"type":"Place","valz":0,"building":"Campus","valy":684},{"valx":1340,"globalY":702,"isWalkable":true,"globalX":1340,"floorMap":"Campus Map","name":"Campus:1340:702:0","isPlace":false,"type":"Place","valz":0,"building":"Campus","valy":702},{"valx":1389,"globalY":711,"isWalkable":true,"globalX":1389,"floorMap":"Campus Map","name":"Campus:1389:711:0","isPlace":false,"type":"Place","valz":0,"building":"Campus","valy":711},{"valx":1456,"globalY":726,"isWalkable":true,"globalX":1456,"floorMap":"Campus Map","name":"Gordon Library Front Entrance","isPlace":false,"type":"Transition Point","valz":0,"building":"Campus","valy":726},{"valx":1336,"globalY":950,"isWalkable":true,"globalX":1336,"floorMap":"Campus Map","name":"Campus:1336:950:1","isPlace":false,"type":"Place","valz":1,"building":"Campus","valy":950},{"valx":1218,"globalY":834,"isWalkable":true,"globalX":1218,"floorMap":"Campus Map","name":"Campus:1218:834:0","isPlace":false,"type":"Place","valz":0,"building":"Campus","valy":834},{"valx":1247,"globalY":938,"isWalkable":true,"globalX":1247,"floorMap":"Campus Map","name":"Campus:1247:938:1","isPlace":false,"type":"Place","valz":1,"building":"Campus","valy":938},{"valx":1412,"globalY":714,"isWalkable":true,"globalX":1412,"floorMap":"Campus Map","name":"Campus:1412:417:0","isPlace":false,"type":"Place","valz":0,"building":"Campus","valy":714},{"valx":1431,"globalY":594,"isWalkable":true,"globalX":1431,"floorMap":"Campus Map","name":"Campus:1431:594:-1","isPlace":false,"type":"Place","valz":-1,"building":"Campus","valy":594},{"valx":1417,"globalY":566,"isWalkable":true,"globalX":1417,"floorMap":"Campus Map","name":"Campus:1417:566:-1","isPlace":false,"type":"Place","valz":-1,"building":"Campus","valy":566},{"valx":1425,"globalY":550,"isWalkable":true,"globalX":1425,"floorMap":"Campus Map","name":"Campus:1425:550:-1","isPlace":false,"type":"Place","valz":-1,"building":"Campus","valy":550},{"valx":1376,"globalY":539,"isWalkable":true,"globalX":1376,"floorMap":"Campus Map","name":"Campus:1376:539:-1","isPlace":false,"type":"Place","valz":-1,"building":"Campus","valy":539},{"valx":1383,"globalY":550,"isWalkable":true,"globalX":1383,"floorMap":"Campus Map","name":"Campus:1383:550:-1","isPlace":false,"type":"Place","valz":-1,"building":"Campus","valy":550},{"valx":1457,"globalY":611,"isWalkable":true,"globalX":1457,"floorMap":"Campus Map","name":"Campus:1457:611:-1","isPlace":false,"type":"Place","valz":-1,"building":"Campus","valy":611},{"valx":1541,"globalY":570,"isWalkable":true,"globalX":1541,"floorMap":"Campus Map","name":"Campus:1541:570:-3","isPlace":false,"type":"Place","valz":-3,"building":"Campus","valy":570},{"valx":1579,"globalY":647,"isWalkable":true,"globalX":1579,"floorMap":"Campus Map","name":"Campus:1579:647:-4","isPlace":false,"type":"Place","valz":-4,"building":"Campus","valy":647},{"valx":1617,"globalY":632,"isWalkable":true,"globalX":1617,"floorMap":"Campus Map","name":"Campus:1617:632:-4","isPlace":false,"type":"Place","valz":-4,"building":"Campus","valy":632},{"valx":1110,"globalY":462,"isWalkable":true,"globalX":1110,"floorMap":"Campus Map","name":"Campus:1110:462:0","isPlace":false,"type":"Place","valz":-1,"building":"Campus","valy":462},{"valx":1099,"globalY":516,"isWalkable":true,"globalX":1099,"floorMap":"Campus Map","name":"Campus:1099:516:0","isPlace":false,"type":"Place","valz":-1,"building":"Campus","valy":516},{"valx":1073,"globalY":560,"isWalkable":true,"globalX":1073,"floorMap":"Campus Map","name":"Campus:1073:560:0","isPlace":false,"type":"Place","valz":-1,"building":"Campus","valy":560},{"valx":1101,"globalY":810,"isWalkable":true,"globalX":1101,"floorMap":"Campus Map","name":"Campus:1101:810:0","isPlace":false,"type":"Place","valz":0,"building":"Campus","valy":810},{"valx":1069,"globalY":803,"isWalkable":true,"globalX":1069,"floorMap":"Campus Map","name":"Campus:1069:803:0","isPlace":false,"type":"Place","valz":0,"building":"Campus","valy":803},{"valx":1060,"globalY":855,"isWalkable":true,"globalX":1060,"floorMap":"Campus Map","name":"Campus:1060:855:0","isPlace":false,"type":"Place","valz":0,"building":"Campus","valy":855},{"valx":1071,"globalY":788,"isWalkable":true,"globalX":1071,"floorMap":"Campus Map","name":"Campus:1071:788:0","isPlace":false,"type":"Place","valz":0,"building":"Campus","valy":788},{"valx":976,"globalY":770,"isWalkable":true,"globalX":976,"floorMap":"Campus Map","name":"Campus:976:770:0","isPlace":false,"type":"Place","valz":0,"building":"Campus","valy":770},{"valx":1050,"globalY":733,"isWalkable":true,"globalX":1049,"floorMap":"Campus Map","name":"Campus:1050:732:0","isPlace":false,"type":"Place","valz":0,"building":"Campus","valy":732},{"valx":941,"globalY":735,"isWalkable":true,"globalX":941,"floorMap":"Campus Map","name":"Campus:941:735:0","isPlace":false,"type":"Place","valz":0,"building":"Campus","valy":735},{"valx":965,"globalY":718,"isWalkable":true,"globalX":965,"floorMap":"Campus Map","name":"Campus:965:718:0","isPlace":false,"type":"Place","valz":0,"building":"Campus","valy":718},{"valx":1048,"globalY":922,"isWalkable":true,"globalX":1048,"floorMap":"Campus Map","name":"Campus:1048:922:0","isPlace":false,"type":"Place","valz":0,"building":"Campus","valy":922},{"valx":1044,"globalY":951,"isWalkable":true,"globalX":1044,"floorMap":"Campus Map","name":"Campus:1044:951:0","isPlace":false,"type":"Place","valz":0,"building":"Campus","valy":951},{"valx":1025,"globalY":950,"isWalkable":true,"globalX":1025,"floorMap":"Campus Map","name":"Campus:1025:950:0","isPlace":false,"type":"Place","valz":0,"building":"Campus","valy":950},{"valx":964,"globalY":907,"isWalkable":true,"globalX":964,"floorMap":"Campus Map","name":"Campus:964:907:0","isPlace":false,"type":"Place","valz":0,"building":"Campus","valy":907},{"valx":949,"globalY":912,"isWalkable":true,"globalX":949,"floorMap":"Campus Map","name":"Campus:949:912:0","isPlace":false,"type":"Place","valz":0,"building":"Campus","valy":912},{"valx":1093,"globalY":914,"isWalkable":true,"globalX":1093,"floorMap":"Campus Map","name":"Campus:1093:914:0","isPlace":false,"type":"Place","valz":0,"building":"Campus","valy":914},{"valx":1071,"globalY":935,"isWalkable":true,"globalX":1071,"floorMap":"Campus Map","name":"Campus:1071:935:0","isPlace":false,"type":"Place","valz":0,"building":"Campus","valy":935},{"valx":847,"globalY":916,"isWalkable":true,"globalX":847,"floorMap":"Campus Map","name":"Campus:847:916:0","isPlace":false,"type":"Place","valz":0,"building":"Campus","valy":916},{"valx":790,"globalY":883,"isWalkable":true,"globalX":790,"floorMap":"Campus Map","name":"Campus:790:883:0","isPlace":false,"type":"Place","valz":0,"building":"Campus","valy":883},{"valx":805,"globalY":905,"isWalkable":true,"globalX":805,"floorMap":"Campus Map","name":"Campus:805:905:0","isPlace":false,"type":"Place","valz":0,"building":"Campus","valy":905},{"valx":821,"globalY":755,"isWalkable":true,"globalX":821,"floorMap":"Campus Map","name":"Campus:821:775:0","isPlace":false,"type":"Place","valz":0,"building":"Campus","valy":755},{"valx":918,"globalY":929,"isWalkable":true,"globalX":918,"floorMap":"Campus Map","name":"Campus:918:929:0","isPlace":false,"type":"Place","valz":0,"building":"Campus","valy":929},{"valx":877,"globalY":733,"isWalkable":true,"globalX":877,"floorMap":"Campus Map","name":"Campus:877:733:0","isPlace":false,"type":"Place","valz":0,"building":"Campus","valy":733},{"valx":789,"globalY":805,"isWalkable":true,"globalX":789,"floorMap":"Campus Map","name":"Campus:789:805:0","isPlace":false,"type":"Place","valz":0,"building":"Campus","valy":805},{"valx":816,"globalY":709,"isWalkable":true,"globalX":816,"floorMap":"Campus Map","name":"Campus:816:709:0","isPlace":false,"type":"Place","valz":0,"building":"Campus","valy":709},{"valx":827,"globalY":726,"isWalkable":true,"globalX":827,"floorMap":"Campus Map","name":"Campus:827:726:0","isPlace":false,"type":"Place","valz":0,"building":"Campus","valy":726},{"valx":1263,"globalY":446,"isWalkable":true,"globalX":1263,"floorMap":"Campus Map","name":"Campus:1263:446","isPlace":false,"type":"Place","valz":0,"building":"Campus","valy":446},{"valx":1290,"globalY":449,"isWalkable":true,"globalX":1290,"floorMap":"Campus Map","name":"Campus:1290:449","isPlace":false,"type":"Place","valz":0,"building":"Campus","valy":449},{"valx":1139,"globalY":409,"isWalkable":true,"globalX":1139,"floorMap":"Campus Map","name":"Campus:1139:409:0","isPlace":false,"type":"Place","valz":0,"building":"Campus","valy":409},{"valx":1112,"globalY":407,"isWalkable":true,"globalX":1112,"floorMap":"Campus Map","name":"Campus:1112:407:0","isPlace":false,"type":"Place","valz":-1,"building":"Campus","valy":407},{"valx":1099,"globalY":400,"isWalkable":true,"globalX":1099,"floorMap":"Campus Map","name":"Campus:1099:400:0","isPlace":false,"type":"Place","valz":-1,"building":"Campus","valy":400},{"valx":1076,"globalY":436,"isWalkable":true,"globalX":1076,"floorMap":"Campus Map","name":"Campus:1076:436:0","isPlace":false,"type":"Place","valz":-1,"building":"Campus","valy":436},{"valx":1058,"globalY":425,"isWalkable":true,"globalX":1058,"floorMap":"Campus Map","name":"Higgins House Entrance","isPlace":false,"type":"Transition Point","valz":-2,"building":"Campus","valy":425},{"valx":1343,"globalY":529,"isWalkable":true,"globalX":1343,"floorMap":"Campus Map","name":"Campus:1343:529:-1","isPlace":false,"type":"Place","valz":-1,"building":"Campus","valy":529},{"valx":1302,"globalY":510,"isWalkable":true,"globalX":1302,"floorMap":"Campus Map","name":"Campus:1302:510:-1","isPlace":false,"type":"Place","valz":-1,"building":"Campus","valy":510},{"valx":1200,"globalY":871,"isWalkable":true,"globalX":1200,"floorMap":"Campus Map","name":"Campus:1200:871:0","isPlace":false,"type":"Place","valz":0,"building":"Campus","valy":871},{"valx":1174,"globalY":903,"isWalkable":true,"globalX":1174,"floorMap":"Campus Map","name":"Campus:1174:903:0","isPlace":false,"type":"Place","valz":0,"building":"Campus","valy":903},{"valx":1242,"globalY":809,"isWalkable":true,"globalX":1242,"floorMap":"Campus Map","name":"CampusMap:1242:809","isPlace":false,"type":"Transition Point","valz":0,"building":"Campus","valy":809},{"valx":489,"globalY":279,"isWalkable":true,"globalX":489,"floorMap":"Campus Map","name":"CampusMap:489:279","isPlace":false,"type":"Place","valz":0,"building":"Campus","valy":279},{"valx":559,"globalY":277,"isWalkable":true,"globalX":559,"floorMap":"Campus Map","name":"CampusMap:559:277","isPlace":false,"type":"Place","valz":0,"building":"Campus","valy":277},{"valx":693,"globalY":276,"isWalkable":true,"globalX":693,"floorMap":"Campus Map","name":"CampusMap:693:276","isPlace":false,"type":"Place","valz":0,"building":"Campus","valy":276},{"valx":809,"globalY":367,"isWalkable":true,"globalX":809,"floorMap":"Campus Map","name":"CampusMap:809:367","isPlace":false,"type":"Place","valz":0,"building":"Campus","valy":367},{"valx":935,"globalY":367,"isWalkable":true,"globalX":935,"floorMap":"Campus Map","name":"CampusMap:935:367","isPlace":false,"type":"Place","valz":0,"building":"Campus","valy":367},{"valx":786,"globalY":367,"isWalkable":true,"globalX":786,"floorMap":"Campus Map","name":"CampusMap:786:367","isPlace":false,"type":"Place","valz":0,"building":"Campus","valy":367},{"valx":617,"globalY":276,"isWalkable":true,"globalX":617,"floorMap":"Campus Map","name":"CampusMap:617:276","isPlace":false,"type":"Place","valz":0,"building":"Campus","valy":276},{"valx":759,"globalY":276,"isWalkable":true,"globalX":759,"floorMap":"Campus Map","name":"CampusMap:759:276","isPlace":false,"type":"Place","valz":0,"building":"Campus","valy":276},{"valx":843,"globalY":276,"isWalkable":true,"globalX":843,"floorMap":"Campus Map","name":"CampusMap:843:276","isPlace":false,"type":"Place","valz":0,"building":"Campus","valy":276},{"valx":897,"globalY":276,"isWalkable":true,"globalX":897,"floorMap":"Campus Map","name":"CampusMap:897:276","isPlace":false,"type":"Place","valz":0,"building":"Campus","valy":276},{"valx":438,"globalY":279,"isWalkable":true,"globalX":438,"floorMap":"Campus Map","name":"CampusMap:438:279","isPlace":true,"type":"Place","valz":0,"building":"Campus","valy":279},{"valx":742,"globalY":367,"isWalkable":true,"globalX":742,"floorMap":"Campus Map","name":"CampusMap:742:367","isPlace":true,"type":"Place","valz":0,"building":"Campus","valy":367}]
